asix_Sergio_Belmonte/asix_Sergio_Belmonte.py
asix_Sergio_Belmonte-0.1.dist-info/METADATA
asix_Sergio_Belmonte-0.1.dist-info/WHEEL
asix_Sergio_Belmonte-0.1.dist-info/top_level.txt
asix_Sergio_Belmonte-0.1.dist-info/RECORD
