Metadata-Version: 2.1
Name: asix-Sergio-Belmonte
Version: 0.1
Summary: Sube paquete
Author: Belmonte
